eru/__init__.py
eru/metrics.py
eru/train.py
eru/layers/__init__.py
eru/layers/activation.py
eru/layers/base.py
eru/layers/embedding.py
eru/layers/linear.py
eru/layers/other.py
eru/layers/rnn.py
eru/model/__init__.py
eru/model/model.py
eru/model/sequential.py
eru/utils/__init__.py
eru/utils/data.py
eru/utils/muti_class_seq_data.py
eru/utils/utils.py
eru-0.0.1.dist-info/DESCRIPTION.rst
eru-0.0.1.dist-info/METADATA
eru-0.0.1.dist-info/RECORD
eru-0.0.1.dist-info/WHEEL
eru-0.0.1.dist-info/metadata.json
eru-0.0.1.dist-info/top_level.txt
