Metadata-Version: 2.0
Name: eru
Version: 0.0.1
Summary: Deep Learning for all
Home-page: https://github.com/Shawn-Shan/eru
Author: Shawn Shan
Author-email: shansixioing@uchicago.edu
License: MIT
Platform: UNKNOWN
Classifier: Intended Audience :: Developers
Classifier: Intended Audience :: Education
Classifier: Intended Audience :: Science/Research
Classifier: License :: OSI Approved :: MIT License
Classifier: Programming Language :: Python :: 3.6
Classifier: Topic :: Software Development :: Libraries
Classifier: Topic :: Software Development :: Libraries :: Python Modules
